MANIFEST.in
README.md
setup.py
GXBubble.egg-info/PKG-INFO
GXBubble.egg-info/SOURCES.txt
GXBubble.egg-info/dependency_links.txt
GXBubble.egg-info/not-zip-safe
GXBubble.egg-info/top_level.txt
gxbubble/__init__.py
gxbubble/asset_cli.py
gxbubble/iOSBuild.py
gxbubble/sh.py
gxbubble/tail.py
gxbubble/task.py
gxbubble/unity.py