Metadata-Version: 1.0
Name: GXBubble
Version: 0.1.26
Summary: GameBox Bubble Python Package
Home-page: UNKNOWN
Author: mouguangyi
Author-email: mouguangyi@ztgame.com
License: MIT
Platform: UNKNOWN
